pyeasyremote/__init__.py
pyeasyremote/easyremote.py
pyeasyremote-1.0.dist-info/LICENSE
pyeasyremote-1.0.dist-info/METADATA
pyeasyremote-1.0.dist-info/WHEEL
pyeasyremote-1.0.dist-info/top_level.txt
pyeasyremote-1.0.dist-info/RECORD
