Metadata-Version: 2.1
Name: pyeasyremote
Version: 1.0
Summary: Control Easy Remote supporting DMX lighting control software using python
Home-page: https://github.com/Jeroen-45/pyeasyremote
Author: Jeroen Tas
Author-email: hi@j45.nl
License: UNKNOWN
Platform: UNKNOWN
Classifier: Programming Language :: Python :: 3
Classifier: License :: OSI Approved :: MIT License
Classifier: Operating System :: OS Independent
Requires-Python: >=3.6
License-File: LICENSE
